{
  "solver_status": 2,
  "feasible": true,
  "mb_formulation_version": 6,
  "runtime": 59.01821994781494,
  "wall_time": 59.018234729766846,
  "mip_gap": 0.00895339177279302,
  "objective": 3.857846050056405,
  "revenue_in_sample": 3.688849744997342,
  "model_num_vars": 6281,
  "model_num_binvars": 1550,
  "model_num_constrs": 10471,
  "bundle_space_size": 32,
  "subadditivity_mode": "full_partition",
  "policy_scope": "full_bundle_prices",
  "bundle_prices": {
    "2": 10.76197480900831,
    "4": 9.21721991657584,
    "5": 21.4322988840497,
    "8": 4.995913807950934,
    "10": 14.904545369123205,
    "11": 27.277336969543313,
    "13": 24.880558869456884,
    "16": 2.1960831294466807,
    "17": 16.694715102126626,
    "18": 11.832857423930752,
    "20": 10.232672048301716,
    "21": 22.61090471467898,
    "22": 18.086616649966228,
    "23": 32.71423341201525,
    "24": 5.465142694439271,
    "25": 19.753626487527793,
    "26": 15.9318808105075,
    "29": 26.721759092559676
  },
  "bundle_prices_full": {
    "0": 0.0,
    "1": 25.13352190286585,
    "2": 10.76197480900831,
    "3": 26.32420439867697,
    "4": 9.21721991657584,
    "5": 21.4322988840497,
    "6": 19.979194725584186,
    "7": 32.1942732807064,
    "8": 4.995913807950934,
    "9": 22.26962259272465,
    "10": 14.904545369123205,
    "11": 27.277336969543313,
    "12": 14.213133724526797,
    "13": 24.880558869456884,
    "14": 22.94630950774605,
    "15": 33.54422036285835,
    "16": 2.1960831294466807,
    "17": 16.694715102126626,
    "18": 11.832857423930752,
    "19": 26.11545520460017,
    "20": 10.232672048301716,
    "21": 22.61090471467898,
    "22": 18.086616649966228,
    "23": 32.71423341201525,
    "24": 5.465142694439271,
    "25": 19.753626487527793,
    "26": 15.9318808105075,
    "27": 29.008094324176486,
    "28": 13.985341567721967,
    "29": 26.721759092559676,
    "30": 20.179635595380056,
    "31": 34.644977026948375
  },
  "bundle_prices_selected": {
    "2": 10.76197480900831,
    "4": 9.21721991657584,
    "5": 21.4322988840497,
    "8": 4.995913807950934,
    "10": 14.904545369123205,
    "11": 27.277336969543313,
    "13": 24.880558869456884,
    "16": 2.1960831294466807,
    "17": 16.694715102126626,
    "18": 11.832857423930752,
    "20": 10.232672048301716,
    "21": 22.61090471467898,
    "22": 18.086616649966228,
    "23": 32.71423341201525,
    "24": 5.465142694439271,
    "25": 19.753626487527793,
    "26": 15.9318808105075,
    "29": 26.721759092559676
  },
  "chosen_bundle_idx_by_customer": [
    23,
    26,
    21,
    2,
    0,
    24,
    5,
    20,
    16,
    0,
    0,
    0,
    21,
    2,
    20,
    24,
    11,
    18,
    0,
    18,
    17,
    0,
    24,
    4,
    0,
    21,
    22,
    13,
    4,
    25,
    5,
    17,
    21,
    24,
    29,
    26,
    8,
    2,
    0,
    10,
    0,
    20,
    26,
    2,
    8,
    18,
    0,
    16,
    5,
    10
  ],
  "chosen_product_matrix": [
    [
      1,
      0,
      1,
      1,
      1
    ],
    [
      1,
      1,
      0,
      1,
      0
    ],
    [
      1,
      0,
      1,
      0,
      1
    ],
    [
      0,
      0,
      0,
      1,
      0
    ],
    [
      0,
      0,
      0,
      0,
      0
    ],
    [
      1,
      1,
      0,
      0,
      0
    ],
    [
      0,
      0,
      1,
      0,
      1
    ],
    [
      1,
      0,
      1,
      0,
      0
    ],
    [
      1,
      0,
      0,
      0,
      0
    ],
    [
      0,
      0,
      0,
      0,
      0
    ],
    [
      0,
      0,
      0,
      0,
      0
    ],
    [
      0,
      0,
      0,
      0,
      0
    ],
    [
      1,
      0,
      1,
      0,
      1
    ],
    [
      0,
      0,
      0,
      1,
      0
    ],
    [
      1,
      0,
      1,
      0,
      0
    ],
    [
      1,
      1,
      0,
      0,
      0
    ],
    [
      0,
      1,
      0,
      1,
      1
    ],
    [
      1,
      0,
      0,
      1,
      0
    ],
    [
      0,
      0,
      0,
      0,
      0
    ],
    [
      1,
      0,
      0,
      1,
      0
    ],
    [
      1,
      0,
      0,
      0,
      1
    ],
    [
      0,
      0,
      0,
      0,
      0
    ],
    [
      1,
      1,
      0,
      0,
      0
    ],
    [
      0,
      0,
      1,
      0,
      0
    ],
    [
      0,
      0,
      0,
      0,
      0
    ],
    [
      1,
      0,
      1,
      0,
      1
    ],
    [
      1,
      0,
      1,
      1,
      0
    ],
    [
      0,
      1,
      1,
      0,
      1
    ],
    [
      0,
      0,
      1,
      0,
      0
    ],
    [
      1,
      1,
      0,
      0,
      1
    ],
    [
      0,
      0,
      1,
      0,
      1
    ],
    [
      1,
      0,
      0,
      0,
      1
    ],
    [
      1,
      0,
      1,
      0,
      1
    ],
    [
      1,
      1,
      0,
      0,
      0
    ],
    [
      1,
      1,
      1,
      0,
      1
    ],
    [
      1,
      1,
      0,
      1,
      0
    ],
    [
      0,
      1,
      0,
      0,
      0
    ],
    [
      0,
      0,
      0,
      1,
      0
    ],
    [
      0,
      0,
      0,
      0,
      0
    ],
    [
      0,
      1,
      0,
      1,
      0
    ],
    [
      0,
      0,
      0,
      0,
      0
    ],
    [
      1,
      0,
      1,
      0,
      0
    ],
    [
      1,
      1,
      0,
      1,
      0
    ],
    [
      0,
      0,
      0,
      1,
      0
    ],
    [
      0,
      1,
      0,
      0,
      0
    ],
    [
      1,
      0,
      0,
      1,
      0
    ],
    [
      0,
      0,
      0,
      0,
      0
    ],
    [
      1,
      0,
      0,
      0,
      0
    ],
    [
      0,
      0,
      1,
      0,
      1
    ],
    [
      0,
      1,
      0,
      1,
      0
    ]
  ],
  "assortments": [
    [
      0,
      0,
      0,
      0,
      0
    ],
    [
      0,
      0,
      0,
      0,
      1
    ],
    [
      0,
      0,
      0,
      1,
      0
    ],
    [
      0,
      0,
      0,
      1,
      1
    ],
    [
      0,
      0,
      1,
      0,
      0
    ],
    [
      0,
      0,
      1,
      0,
      1
    ],
    [
      0,
      0,
      1,
      1,
      0
    ],
    [
      0,
      0,
      1,
      1,
      1
    ],
    [
      0,
      1,
      0,
      0,
      0
    ],
    [
      0,
      1,
      0,
      0,
      1
    ],
    [
      0,
      1,
      0,
      1,
      0
    ],
    [
      0,
      1,
      0,
      1,
      1
    ],
    [
      0,
      1,
      1,
      0,
      0
    ],
    [
      0,
      1,
      1,
      0,
      1
    ],
    [
      0,
      1,
      1,
      1,
      0
    ],
    [
      0,
      1,
      1,
      1,
      1
    ],
    [
      1,
      0,
      0,
      0,
      0
    ],
    [
      1,
      0,
      0,
      0,
      1
    ],
    [
      1,
      0,
      0,
      1,
      0
    ],
    [
      1,
      0,
      0,
      1,
      1
    ],
    [
      1,
      0,
      1,
      0,
      0
    ],
    [
      1,
      0,
      1,
      0,
      1
    ],
    [
      1,
      0,
      1,
      1,
      0
    ],
    [
      1,
      0,
      1,
      1,
      1
    ],
    [
      1,
      1,
      0,
      0,
      0
    ],
    [
      1,
      1,
      0,
      0,
      1
    ],
    [
      1,
      1,
      0,
      1,
      0
    ],
    [
      1,
      1,
      0,
      1,
      1
    ],
    [
      1,
      1,
      1,
      0,
      0
    ],
    [
      1,
      1,
      1,
      0,
      1
    ],
    [
      1,
      1,
      1,
      1,
      0
    ],
    [
      1,
      1,
      1,
      1,
      1
    ]
  ]
}