{
  "solver_status": 2,
  "feasible": true,
  "mb_formulation_version": 5,
  "runtime": 34.969484090805054,
  "wall_time": 34.97125697135925,
  "mip_gap": 0.009219455988434053,
  "objective": 1.6581819068777792,
  "bundle_space_size": 32,
  "policy_scope": "full_bundle_prices",
  "bundle_prices": {
    "0": 0.0,
    "2": 7.955221106976522,
    "4": 6.106586471525983,
    "5": 16.31563522308868,
    "6": 13.697372304779929,
    "7": 23.979472155193893,
    "9": 13.876613756438655,
    "10": 11.758837098735507,
    "11": 21.387681437958772,
    "12": 9.661790895972448,
    "14": 17.266221199870145,
    "15": 27.138982897656586,
    "16": 1.8190244728033755,
    "17": 11.65670137733939,
    "20": 7.100431421161263,
    "22": 14.771809572595142,
    "23": 24.580848261636234,
    "26": 12.337923500835974,
    "27": 22.44039284246819,
    "29": 20.76822226098184,
    "30": 17.913765378363056,
    "31": 28.117507535401266
  },
  "bundle_prices_full": {
    "0": 0.0,
    "1": 23.6252373035747,
    "2": 7.955221106976522,
    "3": 23.625237303574124,
    "4": 6.106586471525983,
    "5": 16.31563522308868,
    "6": 13.697372304779929,
    "7": 23.979472155193893,
    "8": 26.709978751393784,
    "9": 13.876613756438655,
    "10": 11.758837098735507,
    "11": 21.387681437958772,
    "12": 9.661790895972448,
    "13": 19.911065354145588,
    "14": 17.266221199870145,
    "15": 27.138982897656586,
    "16": 1.8190244728033755,
    "17": 11.65670137733939,
    "18": 9.77424557977991,
    "19": 19.298804464966874,
    "20": 7.100431421161263,
    "21": 17.763287848864802,
    "22": 14.771809572595142,
    "23": 24.580848261636234,
    "24": 20.094832445401618,
    "25": 15.169613713636254,
    "26": 12.337923500835974,
    "27": 22.44039284246819,
    "28": 10.62056032345286,
    "29": 20.76822226098184,
    "30": 17.913765378363056,
    "31": 28.117507535401266
  },
  "bundle_prices_selected": {
    "0": 0.0,
    "2": 7.955221106976522,
    "4": 6.106586471525983,
    "5": 16.31563522308868,
    "6": 13.697372304779929,
    "7": 23.979472155193893,
    "9": 13.876613756438655,
    "10": 11.758837098735507,
    "11": 21.387681437958772,
    "12": 9.661790895972448,
    "14": 17.266221199870145,
    "15": 27.138982897656586,
    "16": 1.8190244728033755,
    "17": 11.65670137733939,
    "20": 7.100431421161263,
    "22": 14.771809572595142,
    "23": 24.580848261636234,
    "26": 12.337923500835974,
    "27": 22.44039284246819,
    "29": 20.76822226098184,
    "30": 17.913765378363056,
    "31": 28.117507535401266
  },
  "chosen_bundle_idx_by_customer": [
    6,
    7,
    15,
    29,
    23,
    23,
    23,
    23,
    27,
    11,
    31,
    10,
    0,
    17,
    23,
    16,
    23,
    9,
    23,
    26,
    26,
    20,
    15,
    15,
    26,
    14,
    0,
    23,
    27,
    2,
    12,
    27,
    30,
    9,
    15,
    23,
    4,
    30,
    0,
    31,
    5,
    26,
    11,
    30,
    0,
    22,
    0,
    11,
    30,
    15
  ],
  "chosen_product_matrix": [
    [
      0,
      0,
      1,
      1,
      0
    ],
    [
      0,
      0,
      1,
      1,
      1
    ],
    [
      0,
      1,
      1,
      1,
      1
    ],
    [
      1,
      1,
      1,
      0,
      1
    ],
    [
      1,
      0,
      1,
      1,
      1
    ],
    [
      1,
      0,
      1,
      1,
      1
    ],
    [
      1,
      0,
      1,
      1,
      1
    ],
    [
      1,
      0,
      1,
      1,
      1
    ],
    [
      1,
      1,
      0,
      1,
      1
    ],
    [
      0,
      1,
      0,
      1,
      1
    ],
    [
      1,
      1,
      1,
      1,
      1
    ],
    [
      0,
      1,
      0,
      1,
      0
    ],
    [
      0,
      0,
      0,
      0,
      0
    ],
    [
      1,
      0,
      0,
      0,
      1
    ],
    [
      1,
      0,
      1,
      1,
      1
    ],
    [
      1,
      0,
      0,
      0,
      0
    ],
    [
      1,
      0,
      1,
      1,
      1
    ],
    [
      0,
      1,
      0,
      0,
      1
    ],
    [
      1,
      0,
      1,
      1,
      1
    ],
    [
      1,
      1,
      0,
      1,
      0
    ],
    [
      1,
      1,
      0,
      1,
      0
    ],
    [
      1,
      0,
      1,
      0,
      0
    ],
    [
      0,
      1,
      1,
      1,
      1
    ],
    [
      0,
      1,
      1,
      1,
      1
    ],
    [
      1,
      1,
      0,
      1,
      0
    ],
    [
      0,
      1,
      1,
      1,
      0
    ],
    [
      0,
      0,
      0,
      0,
      0
    ],
    [
      1,
      0,
      1,
      1,
      1
    ],
    [
      1,
      1,
      0,
      1,
      1
    ],
    [
      0,
      0,
      0,
      1,
      0
    ],
    [
      0,
      1,
      1,
      0,
      0
    ],
    [
      1,
      1,
      0,
      1,
      1
    ],
    [
      1,
      1,
      1,
      1,
      0
    ],
    [
      0,
      1,
      0,
      0,
      1
    ],
    [
      0,
      1,
      1,
      1,
      1
    ],
    [
      1,
      0,
      1,
      1,
      1
    ],
    [
      0,
      0,
      1,
      0,
      0
    ],
    [
      1,
      1,
      1,
      1,
      0
    ],
    [
      0,
      0,
      0,
      0,
      0
    ],
    [
      1,
      1,
      1,
      1,
      1
    ],
    [
      0,
      0,
      1,
      0,
      1
    ],
    [
      1,
      1,
      0,
      1,
      0
    ],
    [
      0,
      1,
      0,
      1,
      1
    ],
    [
      1,
      1,
      1,
      1,
      0
    ],
    [
      0,
      0,
      0,
      0,
      0
    ],
    [
      1,
      0,
      1,
      1,
      0
    ],
    [
      0,
      0,
      0,
      0,
      0
    ],
    [
      0,
      1,
      0,
      1,
      1
    ],
    [
      1,
      1,
      1,
      1,
      0
    ],
    [
      0,
      1,
      1,
      1,
      1
    ]
  ],
  "assortments": [
    [
      0,
      0,
      0,
      0,
      0
    ],
    [
      0,
      0,
      0,
      0,
      1
    ],
    [
      0,
      0,
      0,
      1,
      0
    ],
    [
      0,
      0,
      0,
      1,
      1
    ],
    [
      0,
      0,
      1,
      0,
      0
    ],
    [
      0,
      0,
      1,
      0,
      1
    ],
    [
      0,
      0,
      1,
      1,
      0
    ],
    [
      0,
      0,
      1,
      1,
      1
    ],
    [
      0,
      1,
      0,
      0,
      0
    ],
    [
      0,
      1,
      0,
      0,
      1
    ],
    [
      0,
      1,
      0,
      1,
      0
    ],
    [
      0,
      1,
      0,
      1,
      1
    ],
    [
      0,
      1,
      1,
      0,
      0
    ],
    [
      0,
      1,
      1,
      0,
      1
    ],
    [
      0,
      1,
      1,
      1,
      0
    ],
    [
      0,
      1,
      1,
      1,
      1
    ],
    [
      1,
      0,
      0,
      0,
      0
    ],
    [
      1,
      0,
      0,
      0,
      1
    ],
    [
      1,
      0,
      0,
      1,
      0
    ],
    [
      1,
      0,
      0,
      1,
      1
    ],
    [
      1,
      0,
      1,
      0,
      0
    ],
    [
      1,
      0,
      1,
      0,
      1
    ],
    [
      1,
      0,
      1,
      1,
      0
    ],
    [
      1,
      0,
      1,
      1,
      1
    ],
    [
      1,
      1,
      0,
      0,
      0
    ],
    [
      1,
      1,
      0,
      0,
      1
    ],
    [
      1,
      1,
      0,
      1,
      0
    ],
    [
      1,
      1,
      0,
      1,
      1
    ],
    [
      1,
      1,
      1,
      0,
      0
    ],
    [
      1,
      1,
      1,
      0,
      1
    ],
    [
      1,
      1,
      1,
      1,
      0
    ],
    [
      1,
      1,
      1,
      1,
      1
    ]
  ]
}