{
  "solver_status": 9,
  "feasible": true,
  "mb_formulation_version": 5,
  "runtime": 300.00949692726135,
  "wall_time": 300.01124811172485,
  "mip_gap": 0.012335648835156253,
  "objective": 1.6874424162995145,
  "bundle_space_size": 32,
  "policy_scope": "full_bundle_prices",
  "bundle_prices": {
    "0": 0.0,
    "2": 8.264000493490732,
    "3": 18.469404582122515,
    "5": 16.05872165221424,
    "6": 13.611333308140281,
    "7": 23.73552044380487,
    "12": 9.300217138439676,
    "13": 19.61475061230974,
    "14": 17.070804420589074,
    "15": 27.442775295623196,
    "17": 11.663814996211435,
    "18": 9.36678855028866,
    "19": 19.32683118377094,
    "21": 17.188942980767763,
    "22": 14.835349702531229,
    "23": 24.89918922856098,
    "25": 15.000241617878173,
    "26": 13.095723831398017,
    "27": 22.840807435118176,
    "28": 10.285851386871173,
    "29": 20.37099077748572,
    "30": 18.336486335792348,
    "31": 27.99427150553264
  },
  "bundle_prices_full": {
    "0": 0.0,
    "1": 29.82582748019356,
    "2": 8.264000493490732,
    "3": 18.469404582122515,
    "4": 29.82582748019356,
    "5": 16.05872165221424,
    "6": 13.611333308140281,
    "7": 23.73552044380487,
    "8": 29.82582748019356,
    "9": 14.117460354760846,
    "10": 11.974056398333392,
    "11": 22.381460848251578,
    "12": 9.300217138439676,
    "13": 19.61475061230974,
    "14": 17.070804420589074,
    "15": 27.442775295623196,
    "16": 1.7998353182099776,
    "17": 11.663814996211435,
    "18": 9.36678855028866,
    "19": 19.32683118377094,
    "20": 7.213292290394488,
    "21": 17.188942980767763,
    "22": 14.835349702531229,
    "23": 24.89918922856098,
    "24": 5.045480503739466,
    "25": 15.000241617878173,
    "26": 13.095723831398017,
    "27": 22.840807435118176,
    "28": 10.285851386871173,
    "29": 20.37099077748572,
    "30": 18.336486335792348,
    "31": 27.99427150553264
  },
  "bundle_prices_selected": {
    "0": 0.0,
    "2": 8.264000493490732,
    "3": 18.469404582122515,
    "5": 16.05872165221424,
    "6": 13.611333308140281,
    "7": 23.73552044380487,
    "12": 9.300217138439676,
    "13": 19.61475061230974,
    "14": 17.070804420589074,
    "15": 27.442775295623196,
    "17": 11.663814996211435,
    "18": 9.36678855028866,
    "19": 19.32683118377094,
    "21": 17.188942980767763,
    "22": 14.835349702531229,
    "23": 24.89918922856098,
    "25": 15.000241617878173,
    "26": 13.095723831398017,
    "27": 22.840807435118176,
    "28": 10.285851386871173,
    "29": 20.37099077748572,
    "30": 18.336486335792348,
    "31": 27.99427150553264
  },
  "chosen_bundle_idx_by_customer": [
    17,
    19,
    2,
    19,
    31,
    0,
    0,
    18,
    31,
    23,
    25,
    21,
    15,
    14,
    30,
    6,
    6,
    31,
    5,
    12,
    5,
    6,
    0,
    26,
    31,
    0,
    7,
    22,
    31,
    19,
    27,
    31,
    18,
    31,
    31,
    12,
    29,
    27,
    13,
    12,
    0,
    22,
    28,
    5,
    19,
    6,
    17,
    13,
    7,
    3
  ],
  "chosen_product_matrix": [
    [
      1,
      0,
      0,
      0,
      1
    ],
    [
      1,
      0,
      0,
      1,
      1
    ],
    [
      0,
      0,
      0,
      1,
      0
    ],
    [
      1,
      0,
      0,
      1,
      1
    ],
    [
      1,
      1,
      1,
      1,
      1
    ],
    [
      0,
      0,
      0,
      0,
      0
    ],
    [
      0,
      0,
      0,
      0,
      0
    ],
    [
      1,
      0,
      0,
      1,
      0
    ],
    [
      1,
      1,
      1,
      1,
      1
    ],
    [
      1,
      0,
      1,
      1,
      1
    ],
    [
      1,
      1,
      0,
      0,
      1
    ],
    [
      1,
      0,
      1,
      0,
      1
    ],
    [
      0,
      1,
      1,
      1,
      1
    ],
    [
      0,
      1,
      1,
      1,
      0
    ],
    [
      1,
      1,
      1,
      1,
      0
    ],
    [
      0,
      0,
      1,
      1,
      0
    ],
    [
      0,
      0,
      1,
      1,
      0
    ],
    [
      1,
      1,
      1,
      1,
      1
    ],
    [
      0,
      0,
      1,
      0,
      1
    ],
    [
      0,
      1,
      1,
      0,
      0
    ],
    [
      0,
      0,
      1,
      0,
      1
    ],
    [
      0,
      0,
      1,
      1,
      0
    ],
    [
      0,
      0,
      0,
      0,
      0
    ],
    [
      1,
      1,
      0,
      1,
      0
    ],
    [
      1,
      1,
      1,
      1,
      1
    ],
    [
      0,
      0,
      0,
      0,
      0
    ],
    [
      0,
      0,
      1,
      1,
      1
    ],
    [
      1,
      0,
      1,
      1,
      0
    ],
    [
      1,
      1,
      1,
      1,
      1
    ],
    [
      1,
      0,
      0,
      1,
      1
    ],
    [
      1,
      1,
      0,
      1,
      1
    ],
    [
      1,
      1,
      1,
      1,
      1
    ],
    [
      1,
      0,
      0,
      1,
      0
    ],
    [
      1,
      1,
      1,
      1,
      1
    ],
    [
      1,
      1,
      1,
      1,
      1
    ],
    [
      0,
      1,
      1,
      0,
      0
    ],
    [
      1,
      1,
      1,
      0,
      1
    ],
    [
      1,
      1,
      0,
      1,
      1
    ],
    [
      0,
      1,
      1,
      0,
      1
    ],
    [
      0,
      1,
      1,
      0,
      0
    ],
    [
      0,
      0,
      0,
      0,
      0
    ],
    [
      1,
      0,
      1,
      1,
      0
    ],
    [
      1,
      1,
      1,
      0,
      0
    ],
    [
      0,
      0,
      1,
      0,
      1
    ],
    [
      1,
      0,
      0,
      1,
      1
    ],
    [
      0,
      0,
      1,
      1,
      0
    ],
    [
      1,
      0,
      0,
      0,
      1
    ],
    [
      0,
      1,
      1,
      0,
      1
    ],
    [
      0,
      0,
      1,
      1,
      1
    ],
    [
      0,
      0,
      0,
      1,
      1
    ]
  ],
  "assortments": [
    [
      0,
      0,
      0,
      0,
      0
    ],
    [
      0,
      0,
      0,
      0,
      1
    ],
    [
      0,
      0,
      0,
      1,
      0
    ],
    [
      0,
      0,
      0,
      1,
      1
    ],
    [
      0,
      0,
      1,
      0,
      0
    ],
    [
      0,
      0,
      1,
      0,
      1
    ],
    [
      0,
      0,
      1,
      1,
      0
    ],
    [
      0,
      0,
      1,
      1,
      1
    ],
    [
      0,
      1,
      0,
      0,
      0
    ],
    [
      0,
      1,
      0,
      0,
      1
    ],
    [
      0,
      1,
      0,
      1,
      0
    ],
    [
      0,
      1,
      0,
      1,
      1
    ],
    [
      0,
      1,
      1,
      0,
      0
    ],
    [
      0,
      1,
      1,
      0,
      1
    ],
    [
      0,
      1,
      1,
      1,
      0
    ],
    [
      0,
      1,
      1,
      1,
      1
    ],
    [
      1,
      0,
      0,
      0,
      0
    ],
    [
      1,
      0,
      0,
      0,
      1
    ],
    [
      1,
      0,
      0,
      1,
      0
    ],
    [
      1,
      0,
      0,
      1,
      1
    ],
    [
      1,
      0,
      1,
      0,
      0
    ],
    [
      1,
      0,
      1,
      0,
      1
    ],
    [
      1,
      0,
      1,
      1,
      0
    ],
    [
      1,
      0,
      1,
      1,
      1
    ],
    [
      1,
      1,
      0,
      0,
      0
    ],
    [
      1,
      1,
      0,
      0,
      1
    ],
    [
      1,
      1,
      0,
      1,
      0
    ],
    [
      1,
      1,
      0,
      1,
      1
    ],
    [
      1,
      1,
      1,
      0,
      0
    ],
    [
      1,
      1,
      1,
      0,
      1
    ],
    [
      1,
      1,
      1,
      1,
      0
    ],
    [
      1,
      1,
      1,
      1,
      1
    ]
  ]
}