{
  "solver_status": 2,
  "feasible": true,
  "mb_formulation_version": 4,
  "runtime": 113.97657203674316,
  "wall_time": 113.97846007347107,
  "mip_gap": 0.009882436950115136,
  "objective": 1.6028275523614286,
  "bundle_space_size": 32,
  "policy_scope": "full_bundle_prices",
  "bundle_prices": {
    "0": 0.0,
    "1": 10.753229709883055,
    "3": 17.904358272222623,
    "4": 5.71701390543559,
    "7": 23.621372177659165,
    "9": 13.999679760712425,
    "10": 11.332624442776668,
    "11": 21.320116206433962,
    "12": 9.39279331297803,
    "13": 19.413929191109883,
    "14": 17.136646997572225,
    "15": 26.660508682855436,
    "16": 1.6113009414034964,
    "21": 16.845806229535356,
    "22": 15.076732634642553,
    "23": 24.578352340857613,
    "25": 14.865224408287759,
    "26": 12.595034135055833,
    "27": 22.521424373714403,
    "29": 20.114563440135885,
    "30": 18.316761678043694,
    "31": 27.65658406667357
  },
  "bundle_prices_full": {
    "0": 0.0,
    "1": 10.753229709883055,
    "2": 28.596622281431774,
    "3": 17.904358272222623,
    "4": 5.71701390543559,
    "5": 16.470243615318687,
    "6": 28.596622281431774,
    "7": 23.621372177659165,
    "8": 26.369791590690077,
    "9": 13.999679760712425,
    "10": 11.332624442776668,
    "11": 21.320116206433962,
    "12": 9.39279331297803,
    "13": 19.413929191109883,
    "14": 17.136646997572225,
    "15": 26.660508682855436,
    "16": 1.6113009414034964,
    "17": 12.36453065128659,
    "18": 22.703313579022527,
    "19": 19.5156592136269,
    "20": 7.328314846839087,
    "21": 16.845806229535356,
    "22": 15.076732634642553,
    "23": 24.578352340857613,
    "24": 20.703796830585883,
    "25": 14.865224408287759,
    "26": 12.595034135055833,
    "27": 22.521424373714403,
    "28": 11.004094254381558,
    "29": 20.114563440135885,
    "30": 18.316761678043694,
    "31": 27.65658406667357
  },
  "bundle_prices_selected": {
    "0": 0.0,
    "1": 10.753229709883055,
    "3": 17.904358272222623,
    "4": 5.71701390543559,
    "7": 23.621372177659165,
    "9": 13.999679760712425,
    "10": 11.332624442776668,
    "11": 21.320116206433962,
    "12": 9.39279331297803,
    "13": 19.413929191109883,
    "14": 17.136646997572225,
    "15": 26.660508682855436,
    "16": 1.6113009414034964,
    "21": 16.845806229535356,
    "22": 15.076732634642553,
    "23": 24.578352340857613,
    "25": 14.865224408287759,
    "26": 12.595034135055833,
    "27": 22.521424373714403,
    "29": 20.114563440135885,
    "30": 18.316761678043694,
    "31": 27.65658406667357
  },
  "chosen_bundle_idx_by_customer": [
    10,
    21,
    3,
    31,
    15,
    3,
    0,
    12,
    15,
    16,
    27,
    15,
    7,
    11,
    4,
    26,
    31,
    9,
    31,
    11,
    22,
    25,
    1,
    21,
    27,
    23,
    7,
    3,
    0,
    23,
    31,
    3,
    31,
    29,
    26,
    27,
    15,
    14,
    0,
    31,
    30,
    4,
    15,
    12,
    13,
    0,
    23,
    15,
    15,
    31
  ],
  "chosen_product_matrix": [
    [
      0,
      1,
      0,
      1,
      0
    ],
    [
      1,
      0,
      1,
      0,
      1
    ],
    [
      0,
      0,
      0,
      1,
      1
    ],
    [
      1,
      1,
      1,
      1,
      1
    ],
    [
      0,
      1,
      1,
      1,
      1
    ],
    [
      0,
      0,
      0,
      1,
      1
    ],
    [
      0,
      0,
      0,
      0,
      0
    ],
    [
      0,
      1,
      1,
      0,
      0
    ],
    [
      0,
      1,
      1,
      1,
      1
    ],
    [
      1,
      0,
      0,
      0,
      0
    ],
    [
      1,
      1,
      0,
      1,
      1
    ],
    [
      0,
      1,
      1,
      1,
      1
    ],
    [
      0,
      0,
      1,
      1,
      1
    ],
    [
      0,
      1,
      0,
      1,
      1
    ],
    [
      0,
      0,
      1,
      0,
      0
    ],
    [
      1,
      1,
      0,
      1,
      0
    ],
    [
      1,
      1,
      1,
      1,
      1
    ],
    [
      0,
      1,
      0,
      0,
      1
    ],
    [
      1,
      1,
      1,
      1,
      1
    ],
    [
      0,
      1,
      0,
      1,
      1
    ],
    [
      1,
      0,
      1,
      1,
      0
    ],
    [
      1,
      1,
      0,
      0,
      1
    ],
    [
      0,
      0,
      0,
      0,
      1
    ],
    [
      1,
      0,
      1,
      0,
      1
    ],
    [
      1,
      1,
      0,
      1,
      1
    ],
    [
      1,
      0,
      1,
      1,
      1
    ],
    [
      0,
      0,
      1,
      1,
      1
    ],
    [
      0,
      0,
      0,
      1,
      1
    ],
    [
      0,
      0,
      0,
      0,
      0
    ],
    [
      1,
      0,
      1,
      1,
      1
    ],
    [
      1,
      1,
      1,
      1,
      1
    ],
    [
      0,
      0,
      0,
      1,
      1
    ],
    [
      1,
      1,
      1,
      1,
      1
    ],
    [
      1,
      1,
      1,
      0,
      1
    ],
    [
      1,
      1,
      0,
      1,
      0
    ],
    [
      1,
      1,
      0,
      1,
      1
    ],
    [
      0,
      1,
      1,
      1,
      1
    ],
    [
      0,
      1,
      1,
      1,
      0
    ],
    [
      0,
      0,
      0,
      0,
      0
    ],
    [
      1,
      1,
      1,
      1,
      1
    ],
    [
      1,
      1,
      1,
      1,
      0
    ],
    [
      0,
      0,
      1,
      0,
      0
    ],
    [
      0,
      1,
      1,
      1,
      1
    ],
    [
      0,
      1,
      1,
      0,
      0
    ],
    [
      0,
      1,
      1,
      0,
      1
    ],
    [
      0,
      0,
      0,
      0,
      0
    ],
    [
      1,
      0,
      1,
      1,
      1
    ],
    [
      0,
      1,
      1,
      1,
      1
    ],
    [
      0,
      1,
      1,
      1,
      1
    ],
    [
      1,
      1,
      1,
      1,
      1
    ]
  ],
  "assortments": [
    [
      0,
      0,
      0,
      0,
      0
    ],
    [
      0,
      0,
      0,
      0,
      1
    ],
    [
      0,
      0,
      0,
      1,
      0
    ],
    [
      0,
      0,
      0,
      1,
      1
    ],
    [
      0,
      0,
      1,
      0,
      0
    ],
    [
      0,
      0,
      1,
      0,
      1
    ],
    [
      0,
      0,
      1,
      1,
      0
    ],
    [
      0,
      0,
      1,
      1,
      1
    ],
    [
      0,
      1,
      0,
      0,
      0
    ],
    [
      0,
      1,
      0,
      0,
      1
    ],
    [
      0,
      1,
      0,
      1,
      0
    ],
    [
      0,
      1,
      0,
      1,
      1
    ],
    [
      0,
      1,
      1,
      0,
      0
    ],
    [
      0,
      1,
      1,
      0,
      1
    ],
    [
      0,
      1,
      1,
      1,
      0
    ],
    [
      0,
      1,
      1,
      1,
      1
    ],
    [
      1,
      0,
      0,
      0,
      0
    ],
    [
      1,
      0,
      0,
      0,
      1
    ],
    [
      1,
      0,
      0,
      1,
      0
    ],
    [
      1,
      0,
      0,
      1,
      1
    ],
    [
      1,
      0,
      1,
      0,
      0
    ],
    [
      1,
      0,
      1,
      0,
      1
    ],
    [
      1,
      0,
      1,
      1,
      0
    ],
    [
      1,
      0,
      1,
      1,
      1
    ],
    [
      1,
      1,
      0,
      0,
      0
    ],
    [
      1,
      1,
      0,
      0,
      1
    ],
    [
      1,
      1,
      0,
      1,
      0
    ],
    [
      1,
      1,
      0,
      1,
      1
    ],
    [
      1,
      1,
      1,
      0,
      0
    ],
    [
      1,
      1,
      1,
      0,
      1
    ],
    [
      1,
      1,
      1,
      1,
      0
    ],
    [
      1,
      1,
      1,
      1,
      1
    ]
  ]
}